robocorp_adapters_custom/__init__.py
robocorp_adapters_custom/_docdb.py
robocorp_adapters_custom/_redis.py
robocorp_adapters_custom/_sqlite.py
robocorp_adapters_custom/_support.py
robocorp_adapters_custom/_types.py
robocorp_adapters_custom/_utils.py
robocorp_adapters_custom/_yorko_control_room.py
robocorp_adapters_custom/exceptions.py
robocorp_adapters_custom/workitems_integration.py
robocorp_adapters_custom-0.1.4.dist-info/METADATA
robocorp_adapters_custom-0.1.4.dist-info/WHEEL
robocorp_adapters_custom-0.1.4.dist-info/top_level.txt
robocorp_adapters_custom-0.1.4.dist-info/RECORD
