Metadata-Version: 2.4
Name: robocorp-adapters-custom
Version: 0.1.4
Summary: Custom Work Item Adapters for Robocorp Producer-Consumer Automation
Author: Josh Yorko
License-Expression: MIT
Project-URL: Homepage, https://github.com/joshyorko/robocorp_adapters_custom
Project-URL: Repository, https://github.com/joshyorko/robocorp_adapters_custom
Project-URL: Documentation, https://github.com/joshyorko/robocorp_adapters_custom/tree/main/docs
Project-URL: Issues, https://github.com/joshyorko/robocorp_adapters_custom/issues
Keywords: robocorp,rpa,automation,work-items,adapters,producer-consumer
Classifier: Development Status :: 4 - Beta
Classifier: Intended Audience :: Developers
Classifier: Operating System :: OS Independent
Classifier: Programming Language :: Python :: 3
Classifier: Programming Language :: Python :: 3.10
Classifier: Programming Language :: Python :: 3.11
Classifier: Programming Language :: Python :: 3.12
Classifier: Topic :: Software Development :: Libraries :: Python Modules
Classifier: Topic :: Office/Business :: Financial
Requires-Python: >=3.10
Requires-Dist: robocorp-workitems>=1.4.0
Requires-Dist: requests>=2.31.0
Requires-Dist: redis>=4.5.0
Requires-Dist: pymongo>=4.3.0
Provides-Extra: dev
Requires-Dist: pytest>=7.4.0; extra == "dev"
Requires-Dist: pytest-cov>=4.1.0; extra == "dev"
Requires-Dist: black>=23.0.0; extra == "dev"
Requires-Dist: ruff>=0.1.0; extra == "dev"
